pier_mob/__init__.py
pier_mob/__main__.py
pier_mob/cli.py
tests/__init__.py
tests/test_app.py
pier_mob_lecovi-0.0.3.2.dist-info/LICENSE
pier_mob_lecovi-0.0.3.2.dist-info/METADATA
pier_mob_lecovi-0.0.3.2.dist-info/WHEEL
pier_mob_lecovi-0.0.3.2.dist-info/entry_points.txt
pier_mob_lecovi-0.0.3.2.dist-info/top_level.txt
pier_mob_lecovi-0.0.3.2.dist-info/RECORD
