Metadata-Version: 2.1
Name: pier-mob-lecovi
Version: 0.0.3.2
Summary: A small example package for creating an executable CLI.
Home-page: https://github.com/lecovi/sample_cli
Author: LeCoVi (Leandro E. Colombo Viña)
Author-email: lecovi@ac.python.org.ar
License: UNKNOWN
Platform: UNKNOWN
Classifier: Programming Language :: Python :: 3
Classifier: License :: OSI Approved :: GNU General Public License v3 or later (GPLv3+)
Classifier: Operating System :: OS Independent
Requires-Python: >=3.6
Requires-Dist: typer
